heliumcli/__init__.py
heliumcli/cli.py
heliumcli/settings.py
heliumcli/utils.py
heliumcli/actions/__init__.py
heliumcli/actions/buildrelease.py
heliumcli/actions/deploybuild.py
heliumcli/actions/init.py
heliumcli/actions/listbuilds.py
heliumcli/actions/prepcode.py
heliumcli/actions/setbuild.py
heliumcli/actions/startservers.py
heliumcli/actions/update.py
heliumcli/actions/updateprojects.py
heliumcli-1.6.35.dist-info/licenses/LICENSE
heliumcli-1.6.35.dist-info/METADATA
heliumcli-1.6.35.dist-info/WHEEL
heliumcli-1.6.35.dist-info/entry_points.txt
heliumcli-1.6.35.dist-info/top_level.txt
heliumcli-1.6.35.dist-info/RECORD
