Metadata-Version: 2.4
Name: heliumcli
Version: 1.6.35
Summary: A CLI tool that provides a useful set of tools for maintaining, building, and deploying code in compatible projects
Author-email: Alex Laird <contact@alexlaird.com>
Maintainer-email: Alex Laird <contact@alexlaird.com>
License-Expression: MIT
Project-URL: Sponsor, https://github.com/sponsors/alexdlaird
Project-URL: Source Code, https://github.com/HeliumEdu/heliumcli
Classifier: Environment :: Console
Classifier: Environment :: Web Environment
Classifier: Intended Audience :: Developers
Classifier: Intended Audience :: System Administrators
Classifier: Operating System :: OS Independent
Classifier: Programming Language :: Python :: 3
Classifier: Programming Language :: Python :: 3.9
Classifier: Programming Language :: Python :: 3.10
Classifier: Programming Language :: Python :: 3.11
Classifier: Programming Language :: Python :: 3.12
Classifier: Programming Language :: Python :: 3.13
Classifier: Topic :: Software Development :: Build Tools
Classifier: Topic :: Software Development :: Testing
Requires-Python: >=3.9
License-File: LICENSE
Requires-Dist: GitPython>=3.0
Requires-Dist: PyYAML>=5.1
Requires-Dist: ansible>=2.10
Requires-Dist: pyngrok>=7.2
Provides-Extra: dev
Requires-Dist: pytest; extra == "dev"
Requires-Dist: coverage[toml]; extra == "dev"
Requires-Dist: flake8; extra == "dev"
Requires-Dist: flake8-pyproject; extra == "dev"
Requires-Dist: pep8-naming; extra == "dev"
Dynamic: license-file
